firefox_bookmarks/__init__.py
firefox_bookmarks/bookmark.py
firefox_bookmarks/connect.py
firefox_bookmarks/constants.py
firefox_bookmarks/locate.py
firefox_bookmarks/models.py
firefox_bookmarks-1.2.0.dist-info/LICENSE
firefox_bookmarks-1.2.0.dist-info/METADATA
firefox_bookmarks-1.2.0.dist-info/WHEEL
firefox_bookmarks-1.2.0.dist-info/RECORD
