Metadata-Version: 2.1
Name: firefox-bookmarks
Version: 1.2.0
Summary: Manage your Firefox bookmarks with ease
Home-page: https://github.com/BURG3R5/firefox-bookmarks
License: AGPL-3.0-or-later
Keywords: firefox,bookmarks,browser,util
Author: Aditya Rajput
Author-email: adiraj20072002@gmail.com
Requires-Python: >=3.10,<4.0
Classifier: Development Status :: 5 - Production/Stable
Classifier: Intended Audience :: Developers
Classifier: Intended Audience :: End Users/Desktop
Classifier: License :: OSI Approved :: GNU Affero General Public License v3 or later (AGPLv3+)
Classifier: Natural Language :: English
Classifier: Operating System :: MacOS
Classifier: Operating System :: Microsoft :: Windows :: Windows 10
Classifier: Operating System :: Microsoft :: Windows :: Windows 11
Classifier: Operating System :: POSIX :: Linux
Classifier: Programming Language :: Python :: 3
Classifier: Programming Language :: Python :: 3.10
Classifier: Programming Language :: Python :: 3.11
Classifier: Topic :: Database
Classifier: Topic :: Internet :: WWW/HTTP :: Browsers
Classifier: Topic :: Software Development :: Libraries :: Python Modules
Classifier: Topic :: Utilities
Requires-Dist: peewee (>=3.16.2,<4.0.0)
Project-URL: Changelog, https://github.com/BURG3R5/firefox-bookmarks/blob/main/CHANGELOG.md
Project-URL: Documentation, https://github.com/BURG3R5/firefox-bookmarks
Project-URL: Repository, https://github.com/BURG3R5/firefox-bookmarks
